initbysql/__init__.py
initbysql/__main__.py
initbysql/templates/app.py.j2
initbysql/templates/crud.py.j2
initbysql/templates/models.py.j2
initbysql/templates/router.py.j2
initbysql/templates/schemas.py.j2
initbysql/templates/auth/crud.py.j2
initbysql/templates/auth/hashutils.py.j2
initbysql/templates/auth/models.py.j2
initbysql/templates/auth/router.py.j2
initbysql/templates/auth/schemas.py.j2
initbysql/templates/auth/utils.py.j2
initbysql-0.3.dist-info/METADATA
initbysql-0.3.dist-info/WHEEL
initbysql-0.3.dist-info/entry_points.txt
initbysql-0.3.dist-info/top_level.txt
initbysql-0.3.dist-info/RECORD
