Metadata-Version: 2.2
Name: initbysql
Version: 0.3
Summary: Автоматическая генерация FastAPI-бэкенда по SQL-скрипту.
Home-page: https://github.com/Viven763/InitBySql
Author: @work_george
Classifier: Programming Language :: Python :: 3
Classifier: License :: OSI Approved :: MIT License
Classifier: Operating System :: OS Independent
Requires-Python: >=3.7
Requires-Dist: Jinja2
Requires-Dist: typer
Requires-Dist: rich
Dynamic: author
Dynamic: classifier
Dynamic: description
Dynamic: description-content-type
Dynamic: home-page
Dynamic: requires-dist
Dynamic: requires-python
Dynamic: summary
